odoo/addons/web_refresher/README.rst
odoo/addons/web_refresher/__init__.py
odoo/addons/web_refresher/__manifest__.py
odoo/addons/web_refresher/i18n/ca.po
odoo/addons/web_refresher/i18n/de.po
odoo/addons/web_refresher/i18n/es.po
odoo/addons/web_refresher/i18n/fr.po
odoo/addons/web_refresher/i18n/hr.po
odoo/addons/web_refresher/i18n/it.po
odoo/addons/web_refresher/i18n/pt_BR.po
odoo/addons/web_refresher/i18n/uk_UA.po
odoo/addons/web_refresher/i18n/web_refresher.pot
odoo/addons/web_refresher/readme/CONTRIBUTORS.md
odoo/addons/web_refresher/readme/DESCRIPTION.md
odoo/addons/web_refresher/static/description/icon.png
odoo/addons/web_refresher/static/description/index.html
odoo/addons/web_refresher/static/description/refresh.png
odoo/addons/web_refresher/static/src/js/control_panel.esm.js
odoo/addons/web_refresher/static/src/js/refresher.esm.js
odoo/addons/web_refresher/static/src/scss/refresher.scss
odoo/addons/web_refresher/static/src/xml/control_panel.xml
odoo/addons/web_refresher/static/src/xml/refresher.xml
odoo_addon_web_refresher-18.0.1.0.0.2.dist-info/METADATA
odoo_addon_web_refresher-18.0.1.0.0.2.dist-info/WHEEL
odoo_addon_web_refresher-18.0.1.0.0.2.dist-info/top_level.txt
odoo_addon_web_refresher-18.0.1.0.0.2.dist-info/RECORD
